webcloner/__init__.py
webcloner/cloner.py
webcloner-1.0.2.dist-info/LICENSE
webcloner-1.0.2.dist-info/METADATA
webcloner-1.0.2.dist-info/WHEEL
webcloner-1.0.2.dist-info/entry_points.txt
webcloner-1.0.2.dist-info/top_level.txt
webcloner-1.0.2.dist-info/RECORD
