Metadata-Version: 2.1
Name: webcloner
Version: 1.0.2
Summary: Offline website cloner, updater, and packager
Home-page: https://github.com/Synthfax/WebCloner
Author: Synthfax
Author-email: synthfax@gmail.com
License: Apache License 2.0
Project-URL: Bug Tracker, https://github.com/Synthfax/WebCloner/issues
Classifier: Programming Language :: Python :: 3
Classifier: Programming Language :: Python :: 3.8
Classifier: License :: OSI Approved :: Apache Software License
Classifier: Operating System :: OS Independent
Classifier: Environment :: Console
Classifier: Topic :: Internet :: WWW/HTTP
Classifier: Topic :: Utilities
Requires-Python: >=3.8
License-File: LICENSE
Requires-Dist: requests>=2.0
Requires-Dist: beautifulsoup4>=4.0
Requires-Dist: tqdm>=4.0
Requires-Dist: flask>=2.0
